[
    {
        "name": "AppCode",
        "icon_path": "icon_AppCode.png",
        "emoji_name": "appcode",
        "channels": [
            {
                "name": "appcode",
                "description": "Smart IDE for iOS/macOS development"
            }
        ],
        "category_name": "Products",
        "subreddit": "AppCode",
        "github": "",
        "product_page": "https://www.jetbrains.com/objc/",
        "description": "Smart IDE for iOS/macOS development",
        "issue_tracker": "OC",
        "aliases": ["objc", "oc"]
    },
    {
        "name": "Aqua",
        "icon_path": "icon_Aqua.png",
        "emoji_name": "aqua",
        "channels": [
            {
                "name": "aqua",
                "description": "A powerful IDE for test automation"
            }
        ],
        "category_name": "Products",
        "subreddit": "",
        "github": "",
        "product_page": "https://www.jetbrains.com/aqua/",
        "description": "A powerful IDE for test automation",
        "issue_tracker": "AQUA",
        "aliases": ["aq", "qa"]
    },
    {
        "name": "CLion",
        "icon_path": "icon_CLion.png",
        "emoji_name": "clion",
        "channels": [
            {
                "name": "clion",
                "description": "A cross-platform IDE for C and C++"
            }
        ],
        "category_name": "Products",
        "subreddit": "",
        "github": "",
        "product_page": "https://www.jetbrains.com/clion/",
        "description": "A cross-platform IDE for C and C++",
        "issue_tracker": "CPP",
        "aliases": ["cl", "cpp"]
    },
    {
        "name": "DataGrip",
        "icon_path": "icon_DataGrip.png",
        "emoji_name": "datagrip",
        "channels": [
            {
                "name": "datagrip",
                "description": "Many databases, one tool"
            }
        ],
        "category_name": "Products",
        "subreddit": "DataGrip",
        "github": "",
        "product_page": "https://www.jetbrains.com/datagrip/",
        "description": "Many databases, one tool",
        "issue_tracker": "DBE",
        "aliases": ["data", "dg", "dbe"]
    },
    {
        "name": "Datalore",
        "icon_path": "icon_Datalore.png",
        "emoji_name": "datalore",
        "channels": [
            {
                "name": "datalore",
                "description": "An intelligent web application for data analysis"
            }
        ],
        "category_name": "Products",
        "subreddit": "Datalore",
        "github": "",
        "product_page": "https://datalore.io/",
        "description": "An intelligent web application for data analysis",
        "issue_tracker": "",
        "aliases": ["dl"]
    },
    {
        "name": "DataSpell",
        "icon_path": "icon_DataSpell.png",
        "emoji_name": "dataspell",
        "channels": [
            {
                "name": "dataspell",
                "description": "A new IDE by JetBrains for data science"
            }
        ],
        "category_name": "Products",
        "subreddit": "dataspell",
        "github": "",
        "product_page": "https://www.jetbrains.com/dataspell/",
        "description": "A new IDE by JetBrains for data science",
        "issue_tracker": "",
        "aliases": ["ds"]
    },
    {
        "name": "dotCover",
        "icon_path": "icon_dotCover.png",
        "emoji_name": "dotcover",
        "channels": [
            {
                "name": "dotcover",
                "description": "The .NET Unit Test Runner and Code Coverage Tool"
            }
        ],
        "category_name": "Products",
        "subreddit": "dotCover",
        "github": "",
        "product_page": "https://www.jetbrains.com/dotcover/",
        "description": "The .NET Unit Test Runner and Code Coverage Tool",
        "issue_tracker": "DCVR",
        "aliases": ["dcvr"]
    },
    {
        "name": "dotMemory",
        "icon_path": "icon_dotMemory.png",
        "emoji_name": "dotmemory",
        "channels": [
            {
                "name": "dotmemory",
                "description": "The .NET Memory Profiler"
            }
        ],
        "category_name": "Products",
        "subreddit": "dotMemory",
        "github": "",
        "product_page": "https://www.jetbrains.com/dotmemory/",
        "description": "The .NET Memory Profiler",
        "issue_tracker": "DMRY",
        "aliases": ["dmry"]
    },
    {
        "name": "dotPeek",
        "icon_path": "icon_dotPeek.png",
        "emoji_name": "dotpeek",
        "channels": [
            {
                "name": "dotpeek",
                "description": "Free .NET Decompiler and Assembly Browser"
            }
        ],
        "category_name": "Products",
        "subreddit": "dotPeek",
        "github": "",
        "product_page": "https://www.jetbrains.com/decompiler/",
        "description": "Free .NET Decompiler and Assembly Browser",
        "issue_tracker": "DOTP",
        "aliases": ["dotp"]
    },
    {
        "name": "dotTrace",
        "icon_path": "icon_dotTrace.png",
        "emoji_name": "dottrace",
        "channels": [
            {
                "name": "dottrace",
                "description": "The .NET Performance Profiler"
            }
        ],
        "category_name": "Products",
        "subreddit": "dotTrace",
        "github": "",
        "product_page": "https://www.jetbrains.com/profiler/",
        "description": ".NET Performance Profiler",
        "issue_tracker": "DTRC",
        "aliases": ["dtrc"]
    },
    {
        "name": "Fleet",
        "icon_path": "icon_Fleet.png",
        "emoji_name": "fleet",
        "channels": [
            {
                "name": "fleet",
                "description": "Next-generation IDE by JetBrains"
            }
        ],
        "category_name": "Products",
        "subreddit": "Fleet",
        "github": "",
        "product_page": "https://www.jetbrains.com/fleet/",
        "description": "Next-generation IDE",
        "issue_tracker": "FL",
        "aliases": ["fl"]
    },
    {
        "name": "Gateway",
        "icon_path": "icon_Gateway.png",
        "emoji_name": "gateway",
        "channels": [
            {
                "name": "gateway",
                "description": "An API gateway for your microservices"
            }
        ],
        "category_name": "Products",
        "subreddit": "JetBrains_Gateway",
        "github": "",
        "product_page": "https://www.jetbrains.com/remote-development/gateway/",
        "description": "Your single entry point to all remote development environments",
        "issue_tracker": "GTW",
        "aliases": ["gtw"]
    },
    {
        "name": "GoLand",
        "icon_path": "icon_GoLand.png",
        "emoji_name": "goland",
        "channels": [
            {
                "name": "goland",
                "description": "Capable and Ergonomic Go IDE"
            }
        ],
        "category_name": "Products",
        "subreddit": "Goland",
        "github": "",
        "product_page": "https://www.jetbrains.com/go/",
        "description": "A Clever IDE to Go",
        "issue_tracker": "GO",
        "aliases": ["go"]
    },
    {
        "name": "Hub",
        "icon_path": "icon_Hub.png",
        "emoji_name": "hub",
        "channels": [
            {
                "name": "hub",
                "description": "The team tool that helps you track, organize and prioritize"
            }
        ],
        "category_name": "Products",
        "subreddit": "JetBrains_Hub",
        "github": "",
        "product_page": "https://www.jetbrains.com/hub/",
        "description": "JetBrains Team Tools, Integrated",
        "issue_tracker": "JPS",
        "aliases": ["jps"]
    },
    {
        "name": "IdeaVim",
        "icon_path": "icon_IdeaVim.png",
        "emoji_name": "ideavim",
        "channels": [
            {
                "name": "ideavim",
                "description": "Vim emulation plug-in for IDEs based on the IntelliJ platform"
            }
        ],
        "category_name": "Open Source",
        "subreddit": "",
        "github": "ideavim",
        "product_page": "https://plugins.jetbrains.com/plugin/164-ideavim",
        "description": "Vim emulation plug-in for IDEs based on the IntelliJ platform",
        "issue_tracker": "VIM",
        "aliases": ["vim"]
    },
    {
        "name": "IntelliJ IDEA Community",
        "icon_path": "icon_IntelliJ_Community.png",
        "emoji_name": "intellijcommunity",
        "channels": [
            {
                "name": "intellij-idea-community",
                "description": "Capable and Ergonomic Java IDE - Community Edition"
            }
        ],
        "category_name": "Open Source",
        "subreddit": "",
        "github": "intellij-community",
        "product_page": "https://www.jetbrains.com/idea/",
        "description": "Capable and Ergonomic Java IDE - Community Edition",
        "issue_tracker": "IDEA",
        "aliases": ["intellij-ce", "idea-ce"]
    },
    {
        "name": "IntelliJ IDEA Edu",
        "icon_path": "icon_IntelliJ_Edu.png",
        "emoji_name": "intellijedu",
        "channels": [
            {
                "name": "intellij-idea-edu",
                "description": "Capable and Ergonomic Java IDE - Educational Edition"
            }
        ],
        "category_name": "Educational",
        "subreddit": "",
        "github": "intellij-community",
        "product_page": "https://www.jetbrains.com/education/learning/java/",
        "description": "Capable and Ergonomic Java IDE - Educational Edition",
        "issue_tracker": "IDEA",
        "aliases": ["intellij-edu", "idea-edu"]
    },
    {
        "name": "IntelliJ IDEA Ultimate",
        "icon_path": "icon_IntelliJ_IDEA.png",
        "emoji_name": "intellijidea",
        "channels": [
            {
                "name": "intellij-idea-ultimate",
                "description": "Capable and Ergonomic Java IDE - Ultimate Edition"
            }
        ],
        "category_name": "Products",
        "subreddit": "",
        "github": "",
        "product_page": "https://www.jetbrains.com/idea/",
        "description": "Capable and Ergonomic Java IDE - Ultimate Edition",
        "issue_tracker": "IDEA",
        "aliases": ["intellij", "idea"]
    },
    {
        "name": "Kotlin",
        "icon_path": "icon_Kotlin.png",
        "emoji_name": "kotlin",
        "channels": [
            {
                "name": "kotlin",
                "description": "A modern programming language that makes developers happier"
            }
        ],
        "category_name": "Open Source",
        "subreddit": "",
        "github": "kotlin",
        "product_page": "https://kotlinlang.org/",
        "description": "Statically typed programming language for the JVM, Android and the browser.",
        "issue_tracker": "KT",
        "aliases": ["kt"]
    },
    {
        "name": "MPS",
        "icon_path": "icon_MPS.png",
        "emoji_name": "mps",
        "channels": [
            {
                "name": "mps",
                "description": "Create your own domain-specific language"
            }
        ],
        "category_name": "Open Source",
        "subreddit": "jetbrains_mps",
        "github": "MPS",
        "product_page": "https://www.jetbrains.com/mps/",
        "description": "Create your own domain-specific language",
        "issue_tracker": "MPS",
        "aliases": []
    },
    {
        "name": "PhpStorm",
        "icon_path": "icon_PhpStorm.png",
        "emoji_name": "phpstorm",
        "channels": [
            {
                "name": "phpstorm",
                "description": "Lightning-smart PHP IDE"
            }
        ],
        "category_name": "Products",
        "subreddit": "",
        "github": "",
        "product_page": "https://www.jetbrains.com/phpstorm/",
        "description": "The Lightning-Smart PHP IDE",
        "issue_tracker": "WI",
        "aliases": ["php", "wi"]
    },
    {
        "name": "Projector",
        "icon_path": "icon_Projector.png",
        "emoji_name": "projector",
        "channels": [
            {
                "name": "projector",
                "description": "Run JetBrains IDEs remotely in the browser"
            }
        ],
        "category_name": "Open Source",
        "subreddit": "JetBrains_Projector",
        "github": "https://github.com/JetBrains/projector-server",
        "product_page": "https://lp.jetbrains.com/projector/",
        "description": "Run JetBrains IDEs and Swing apps remotely over the network",
        "issue_tracker": "PRJ",
        "aliases": ["prj"]
    },
    {
        "name": "PyCharm",
        "icon_path": "icon_PyCharm.png",
        "emoji_name": "pycharm",
        "channels": [
            {
                "name": "pycharm",
                "description": "Python IDE for Professional Developers"
            }
        ],
        "category_name": "Products",
        "subreddit": "pycharm",
        "github": "",
        "product_page": "https://www.jetbrains.com/pycharm/",
        "description": "The Python IDE for Professional Developers",
        "issue_tracker": "PY",
        "aliases": ["python", "py", "pyc"]
    },
    {
        "name": "PyCharm Community",
        "icon_path": "icon_PyCharm_Community.png",
        "emoji_name": "pycharmcommunity",
        "channels": [
            {
                "name": "pycharm-community",
                "description": "Python IDE for Professional Developers - Community Edition"
            }
        ],
        "category_name": "Open Source",
        "subreddit": "pycharm",
        "github": "intellij-community/tree/master/python",
        "product_page": "https://www.jetbrains.com/pycharm/",
        "description": "The Python IDE for Professional Developers - Free Community Edition",
        "issue_tracker": "PY",
        "aliases": ["pycharmce", "pycharm-ce", "pyc-ce", "py-ce", "pyce"]
    },
    {
        "name": "PyCharm Edu",
        "icon_path": "icon_PyCharm_Edu.png",
        "emoji_name": "pycharmedu",
        "channels": [
            {
                "name": "pycharm-edu",
                "description": "Python IDE for Professional Developers - Educational Edition"
            }
        ],
        "category_name": "Educational",
        "subreddit": "pycharm",
        "github": "",
        "product_page": "https://www.jetbrains.com/education/learning/python/",
        "description": "The Python IDE for Professional Developers - Tools dedicated for education",
        "issue_tracker": "PY",
        "aliases": ["pycharmedu", "pyc-edu", "py-edu", "pyedu"]
    },
    {   
        "name": "Qodana",
        "icon_path": "icon_Qodana.png",
        "emoji_name": "qodana",
        "channels": [
            {
                "name": "qodana",
                "description": "Code Quality Platform for CI/CD"
            }
        ],
        "category_name": "Products",
        "subreddit": "Qodana",
        "github": "",
        "product_page": "https://www.jetbrains.com/qodana/",
        "description": "The code quality platform for your favorite CI",
        "issue_tracker": "QD",
        "aliases": ["qd"]
    },
    {
        "name": "ReSharper",
        "icon_path": "icon_ReSharper.png",
        "emoji_name": "resharper",
        "channels": [
            {
                "name": "resharper",
                "description": "The Visual Studio Extension for .NET Developers"
            }
        ],
        "category_name": "Products",
        "subreddit": "ReSharper",
        "github": "",
        "product_page": "https://www.jetbrains.com/resharper/",
        "description": "The Visual Studio Extension for .NET Developers",
        "issue_tracker": "RSRP",
        "aliases": ["rsrp"]
    },
    {
        "name": "ReSharper C++",
        "icon_path": "icon_ReSharper_CPP.png",
        "emoji_name": "resharpercpp",
        "channels": [
            {
                "name": "resharper-cpp",
                "description": "The Visual Studio Extension for C++ Developers"
            }
        ],
        "category_name": "Products",
        "subreddit": "ReSharper",
        "github": "",
        "product_page": "https://www.jetbrains.com/resharper-cpp/",
        "description": "The Visual Studio Extension for C++ Developers",
        "issue_tracker": "RSCPP",
        "aliases": ["rscpp"]
    },
    {
        "name": "ReSharper Ultimate",
        "icon_path": "icon_ReSharper.png",
        "emoji_name": "resharper",
        "channel_name": "",
        "category_name": "",
        "subreddit": "ReSharper",
        "github": "",
        "product_page": "https://www.jetbrains.com/dotnet/",
        "description": "Many .NET developer tools, one license",
        "issue_tracker": "RSRP",
        "aliases": ["dotnet"]
    },
    {
        "name": "Rider",
        "icon_path": "icon_Rider.png",
        "emoji_name": "rider",
        "channels": [
            {
                "name": "rider",
                "description": "Cross-Platform .NET IDE"
            }
        ],
        "category_name": "Products",
        "subreddit": "JetBrains_Rider",
        "github": "",
        "product_page": "https://www.jetbrains.com/rider/",
        "description": "A fast & powerful, cross-platform .NET IDE",
        "issue_tracker": "RIDER",
        "aliases": []
    },
    {
        "name": "RiderFlow",
        "icon_path": "icon_RiderFlow.png",
        "emoji_name": "riderflow",
        "channels": [
            {
                "name": "riderflow",
                "description": "Level Design Tools for Unity"
            }
        ],
        "category_name": "Products",
        "subreddit": "",
        "github": "",
        "product_page": "https://www.jetbrains.com/riderflow/",
        "description": "A scenery tool to build and manage your 3D space",
        "issue_tracker": "RF",
        "aliases": ["rf"]
    },
    {
        "name": "Ring UI",
        "icon_path": "icon_Ring_UI.png",
        "emoji_name": "ringui",
        "channels": [
            {
                "name": "ring-ui",
                "description": "A collection of UI components for web applications"
            }
        ],
        "category_name": "Open Source",
        "subreddit": "",
        "github": "ring-ui",
        "product_page": "https://jetbrains.github.io/ring-ui",
        "description": "A collection of JetBrains Web UI components",
        "issue_tracker": "RG",
        "aliases": ["ring", "rg"]
    },
    {
        "name": "RubyMine",
        "icon_path": "icon_RubyMine.png",
        "emoji_name": "rubymine",
        "channels": [
            {
                "name": "rubymine",
                "description": "The Most Intelligent Ruby and Rails IDE"
            }
        ],
        "category_name": "Products",
        "subreddit": "RubyMine",
        "github": "",
        "product_page": "https://www.jetbrains.com/ruby/",
        "description": "The most intelligent Ruby and Rails IDE developed",
        "issue_tracker": "RUBY",
        "aliases": ["ruby", "rm"]
    },
    {
        "name": "RustRover",
        "icon_path": "icon_RustRover.png",
        "emoji_name": "rustrover",
        "channels": [
            {
                "name": "rustrover",
                "description": "A dedicated IDE for Rust developers"
            }
        ],
        "category_name": "Products",
        "subreddit": "RustRover",
        "github": "",
        "product_page": "https://www.jetbrains.com/rust/",
        "description": "A Standalone IDE for Rust",
        "issue_tracker": "RUST",
        "aliases": ["rust", "rr"]
    },
    {
        "name": "Scala",
        "icon_path": "icon_IntelliJ_Scala.png",
        "emoji_name": "scala",
        "channels": [
            {
                "name": "scala",
                "description": "A programming language that scales with you. Join folks developing and using the Scala plugin in their dedicated Discord server: https://discord.gg/aUKpZzeHCK",
                "permissions": {
                    "send_messages": ["JetBrains"]
                }
            }
        ],
        "category_name": "Open Source",
        "subreddit": "",
        "github": "https://github.com/JetBrains/intellij-scala",
        "product_page": "",
        "description": "Scala plugin for IntelliJ IDEA",
        "issue_tracker": "SCL",
        "aliases": ["scl"]
    },
    {
        "name": "Space",
        "icon_path": "icon_Space.png",
        "emoji_name": "space",
        "channels": [
            {
                "name": "space",
                "description": "The All-in-One Solution for Software Teams"
            }
        ],
        "category_name": "Products",
        "subreddit": "JetBrains_Space",
        "github": "",
        "product_page": "https://www.jetbrains.com/space/",
        "description": "The integrated team environment",
        "issue_tracker": "SPA",
        "aliases": ["spa"]
    },
    {
        "name": "TeamCity",
        "icon_path": "icon_TeamCity.png",
        "emoji_name": "teamcity",
        "channels": [
            {
                "name": "teamcity",
                "description": "Powerful Continuous Integration out of the box"
            }
        ],
        "category_name": "Products",
        "subreddit": "teamcity",
        "github": "",
        "product_page": "https://www.jetbrains.com/teamcity/",
        "description": "Powerful Continuous Integration out of the box",
        "issue_tracker": "TW",
        "aliases": ["tc", "tw"]
    },
    {
        "name": "Toolbox",
        "icon_path": "icon_Toolbox.png",
        "emoji_name": "toolbox",
        "channels": [
            {
                "name": "toolbox",
                "description": "Manage your tools and projects in one place"
            }
        ],
        "category_name": "Products",
        "subreddit": "",
        "github": "",
        "product_page": "https://www.jetbrains.com/toolbox/app/",
        "description": "A control panel for your tools and projects",
        "issue_tracker": "TBX",
        "aliases": ["tb", "tbx"]
    },
    {
        "name": "Upsource",
        "icon_path": "icon_Upsource.png",
        "emoji_name": "upsource",
        "channels": [
            {
                "name": "upsource",
                "description": "Code review, team collaboration, project analytics"
            }
        ],
        "category_name": "Products",
        "subreddit": "Upsource",
        "github": "",
        "product_page": "https://www.jetbrains.com/upsource/",
        "description": "Code review, team collaboration, project analytics",
        "issue_tracker": "UP",
        "aliases": ["up"]
    },
    {
        "name": "WebStorm",
        "icon_path": "icon_WebStorm.png",
        "emoji_name": "webstorm",
        "channels": [
            {
                "name": "webstorm-announcements",
                "description": "Product announcements and updates",
                "permissions": {
                    "send_messages": ["JetBrains"]
                }
            },
            {
                "name": "webstorm-general",
                "description": "General discussions about WebStorm"
            },
            {
                "name": "webstorm-help-hub",
                "description": "Get help with WebStorm",
                "type": "forum",
                "available_tags": [
                    "Angular",
                    "Astro",
                    "CSS",
                    "ESLint",
                    "GraphQL",
                    "HTML",
                    "JS/TS",
                    "JSDocs/TSDoc",
                    "Testing",
                    "Node/Bun/Deno",
                    "Npm/pnpm/yarn",
                    "PostCSS",
                    "Prettier",
                    "Prisma",
                    "React",
                    "Vue",
                    "Tailwind",
                    "Vite",
                    "Bug",
                    "Feature Request",
                    "Performance problem"
                ]
            },
            {
                "name": "webstorm-office-hours",
                "description": "Voice channel for WebStorm office hours",
                "type": "stage_voice"
            },
            {
                "name": "webstorm-ama",
                "description": "Ask Me Anything about WebStorm",
                "type": "forum",
                "permissions": {
                    "send_messages_in_threads": ["JetBrains"]
                }
            }
        ],
        "category_name": "WebStorm",
        "subreddit": "WebStorm",
        "github": "",
        "product_page": "https://www.jetbrains.com/webstorm/",
        "description": "The smartest JavaScript IDE",
        "issue_tracker": "WEB",
        "aliases": ["web"]
    },
    {
        "name": "Writerside",
        "icon_path": "icon_Writerside.png",
        "emoji_name": "writerside",
        "channels": [
            {
                "name": "writerside",
                "description": "A technical authoring and publishing environment"
            }
        ],
        "category_name": "Products",
        "subreddit": "",
        "github": "",
        "product_page": "https://www.jetbrains.com/writerside/",
        "description": "A technical authoring and publishing environment",
        "issue_tracker": "WRS",
        "aliases": ["writer", "wrs"]
    },
    {
        "name": "YouTrack",
        "icon_path": "icon_YouTrack.png",
        "emoji_name": "youtrack",
        "channels": [
            {
                "name": "youtrack",
                "description": "The issue tracker designed for agile software teams"
            }
        ],
        "category_name": "Products",
        "subreddit": "YouTrack",
        "github": "",
        "product_page": "https://www.jetbrains.com/youtrack/",
        "description": "The issue tracker designed for agile software teams",
        "issue_tracker": "JT",
        "aliases": ["yt", "track", "jt"]
    }
]
